bob/__init__.py
bob/pipelines/__init__.py
bob/pipelines/sample.py
bob/pipelines/utils.py
bob/pipelines/wrappers.py
bob/pipelines/xarray.py
bob/pipelines/config/__init__.py
bob/pipelines/config/distributed/__init__.py
bob/pipelines/config/distributed/dask_it_pipeline.py
bob/pipelines/config/distributed/local_p16.py
bob/pipelines/config/distributed/local_p32.py
bob/pipelines/config/distributed/local_p4.py
bob/pipelines/config/distributed/local_p8.py
bob/pipelines/config/distributed/local_parallel.py
bob/pipelines/config/distributed/local_single_thread.py
bob/pipelines/config/distributed/sge_default.py
bob/pipelines/config/distributed/sge_demanding.py
bob/pipelines/config/distributed/sge_gpu.py
bob/pipelines/config/distributed/sge_io_big.py
bob/pipelines/config/distributed/sge_io_big_non_adaptive.py
bob/pipelines/config/distributed/slurm_cpu_default.py
bob/pipelines/dataset/__init__.py
bob/pipelines/dataset/database.py
bob/pipelines/dataset/protocols/__init__.py
bob/pipelines/dataset/protocols/archive.py
bob/pipelines/dataset/protocols/hashing.py
bob/pipelines/dataset/protocols/retrieve.py
bob/pipelines/distributed/__init__.py
bob/pipelines/distributed/sge.py
bob/pipelines/distributed/sge_queues.py
bob/pipelines/transformers/__init__.py
bob/pipelines/transformers/str_to_types.py
bob.pipelines-4.0.1.dist-info/LICENSE
bob.pipelines-4.0.1.dist-info/METADATA
bob.pipelines-4.0.1.dist-info/WHEEL
bob.pipelines-4.0.1.dist-info/entry_points.txt
bob.pipelines-4.0.1.dist-info/top_level.txt
bob.pipelines-4.0.1.dist-info/RECORD
